poincare/__init__.py
poincare/_node.py
poincare/_utils.py
poincare/compile.py
poincare/py.typed
poincare/simulator.py
poincare/solvers.py
poincare/types.py
poincare/units.py
poincare/printing/latex.py
poincare/printing/table.py
poincare/tests/test_comparison.py
poincare/tests/test_derivative.py
poincare/tests/test_equation.py
poincare/tests/test_eval.py
poincare/tests/test_initials.py
poincare/tests/test_inmutability.py
poincare/tests/test_instantiation.py
poincare/tests/test_interact.py
poincare/tests/test_names.py
poincare/tests/test_reactions.py
poincare/tests/test_serialize.py
poincare/tests/test_subclass.py
poincare/tests/test_time.py
poincare/tests/test_units.py
poincare/tests/utils.py
poincare/tests/simulator/test_backends.py
poincare/tests/simulator/test_initials.py
poincare/tests/simulator/test_names.py
poincare/tests/simulator/test_time.py
poincare/tests/simulator/test_transform.py
poincare-0.6.3.dist-info/METADATA
poincare-0.6.3.dist-info/WHEEL
poincare-0.6.3.dist-info/licenses/LICENSE
poincare-0.6.3.dist-info/RECORD
