Metadata-Version: 2.4
Name: poincare
Version: 0.6.3
Summary: Simulation of dynamical systems.
Project-URL: Homepage, https://github.com/maurosilber/poincare
Project-URL: Issues, https://github.com/maurosilber/poincare/issues
Project-URL: Documentation, https://maurosilber.github.io/poincare
Author-email: "Hernán E. Grecco" <hernan.grecco@gmail.com>, Mauro Silberberg <maurosilber@gmail.com>
License: MIT
License-File: LICENSE
Keywords: ODE,differential equations,dynamical systems
Classifier: Intended Audience :: Developers
Classifier: Intended Audience :: Science/Research
Classifier: License :: OSI Approved :: MIT License
Classifier: Operating System :: OS Independent
Classifier: Programming Language :: Python :: 3
Classifier: Programming Language :: Python :: 3.10
Classifier: Programming Language :: Python :: 3.11
Classifier: Programming Language :: Python :: 3.12
Classifier: Programming Language :: Python :: 3.13
Classifier: Topic :: Scientific/Engineering
Classifier: Topic :: Software Development :: Libraries
Requires-Python: >=3.10
Requires-Dist: numpy
Requires-Dist: pandas
Requires-Dist: pint
Requires-Dist: pint-pandas
Requires-Dist: scipy
Requires-Dist: scipy-events>=0.3.1
Requires-Dist: symbolite<0.7,>=0.6.0
Requires-Dist: tabulate
Requires-Dist: typing-extensions
Provides-Extra: interactive
Requires-Dist: ipywidgets; extra == 'interactive'
